[
  {
    "id": "24",
    "name": "Skin KOF",
    "thumb": "uploads/categories/skin_kof_24.png"
  },
  {
    "id": "25",
    "name": "Skin Venom",
    "thumb": "uploads/categories/skin_venom_25.png"
  },
  {
    "id": "26",
    "name": "Skin Lightborn",
    "thumb": "uploads/categories/skin_lightborn_26.png"
  },
  {
    "id": "27",
    "name": "Skin Dragon Tamer",
    "thumb": "uploads/categories/skin_dragon_tamer_27.png"
  },
  {
    "id": "28",
    "name": "Skin Collector",
    "thumb": "uploads/categories/skin_collector_28.png"
  },
  {
    "id": "29",
    "name": "Skin Zodiac",
    "thumb": "uploads/categories/skin_zodiac_29.png"
  },
  {
    "id": "30",
    "name": "Skin Starlight",
    "thumb": "uploads/categories/skin_starlight_30.png"
  },
  {
    "id": "31",
    "name": "Skin Hero",
    "thumb": "uploads/categories/skin_hero_31.png"
  },
  {
    "id": "32",
    "name": "Skin Legend",
    "thumb": "uploads/categories/skin_legend_32.png"
  },
  {
    "id": "33",
    "name": "Others",
    "thumb": "uploads/categories/others_33.png"
  },
  {
    "id": "35",
    "name": "Skin Blazing West",
    "thumb": "uploads/categories/skin_blazing_west_35.png"
  },
  {
    "id": "37",
    "name": "Recall Pack",
    "thumb": "uploads/categories/recall_pack_37.png"
  },
  {
    "id": "42",
    "name": "Skin Stun",
    "thumb": "uploads/categories/skin_stun_42.png"
  },
  {
    "id": "43",
    "name": "Emote Pack",
    "thumb": "uploads/categories/emote_pack_43.png"
  },
  {
    "id": "44",
    "name": "Skin Anime",
    "thumb": "uploads/categories/skin_anime_44.png"
  },
  {
    "id": "45",
    "name": "Skin Starwar",
    "thumb": "uploads/categories/skin_starwar_45.png"
  },
  {
    "id": "48",
    "name": "Skin Custom",
    "thumb": "uploads/categories/skin_custom_48.png"
  },
  {
    "id": "52",
    "name": "Skin Saber",
    "thumb": "uploads/categories/skin_saber_52.png"
  },
  {
    "id": "59",
    "name": "Skin Transformer",
    "thumb": "uploads/categories/skin_transformer_59.png"
  },
  {
    "id": "62",
    "name": "Replace Skin",
    "thumb": "uploads/categories/replace_skin_62.png"
  },
  {
    "id": "64",
    "name": "Skin Lunar",
    "thumb": "uploads/categories/skin_lunar_64.png"
  },
  {
    "id": "65",
    "name": "Skin Abyss",
    "thumb": "uploads/categories/skin_abyss_65.png"
  },
  {
    "id": "66",
    "name": "Skin Aspirant",
    "thumb": "uploads/categories/skin_aspirant_66.png"
  },
  {
    "id": "67",
    "name": "Skin Sanrio",
    "thumb": "uploads/categories/skin_sanrio_67.png"
  },
  {
    "id": "68",
    "name": "Skin MPL",
    "thumb": "uploads/categories/skin_mpl_68.png"
  },
  {
    "id": "69",
    "name": "Skin MWorld",
    "thumb": "uploads/categories/skin_mworld_69.png"
  },
  {
    "id": "77",
    "name": "Skin Exorcist",
    "thumb": "uploads/categories/skin_exorcist_77.webp"
  },
  {
    "id": "78",
    "name": "Skin Kungfu",
    "thumb": "uploads/categories/skin_kungfu_78.webp"
  },
  {
    "id": "79",
    "name": "Skin Saint ",
    "thumb": "uploads/categories/skin_saint_79.png"
  },
  {
    "id": "81",
    "name": "Skin M Series",
    "thumb": "uploads/categories/skin_m_series_81.webp"
  },
  {
    "id": "84",
    "name": "Skin Atomic",
    "thumb": "uploads/categories/skin_atomic_84.webp"
  },
  {
    "id": "85",
    "name": "Skin Jujutsu Kaisen",
    "thumb": "uploads/categories/skin_jujutsu_kaisen_85.webp"
  },
  {
    "id": "87",
    "name": "Skin Beyond Clouds",
    "thumb": "uploads/categories/skin_beyond_clouds_87.webp"
  },
  {
    "id": "98",
    "name": "Skin Neobeast",
    "thumb": "uploads/categories/skin_neobeast_98.webp"
  },
  {
    "id": "99",
    "name": "Skin Mistbender",
    "thumb": "uploads/categories/skin_mistbender_99.webp"
  }
]